odoo/addons/l10n_it_abicab/README.rst
odoo/addons/l10n_it_abicab/__init__.py
odoo/addons/l10n_it_abicab/__manifest__.py
odoo/addons/l10n_it_abicab/i18n/de.po
odoo/addons/l10n_it_abicab/i18n/it.po
odoo/addons/l10n_it_abicab/i18n/l10n_it_abicab.pot
odoo/addons/l10n_it_abicab/i18n/nb_NO.po
odoo/addons/l10n_it_abicab/i18n/sl.po
odoo/addons/l10n_it_abicab/models/__init__.py
odoo/addons/l10n_it_abicab/models/abicab.py
odoo/addons/l10n_it_abicab/readme/CONTRIBUTORS.md
odoo/addons/l10n_it_abicab/readme/DESCRIPTION.md
odoo/addons/l10n_it_abicab/static/description/icon.png
odoo/addons/l10n_it_abicab/static/description/index.html
odoo/addons/l10n_it_abicab/tests/__init__.py
odoo/addons/l10n_it_abicab/tests/test_abicab.py
odoo/addons/l10n_it_abicab/views/abicab_view.xml
odoo_addon_l10n_it_abicab-18.0.1.0.0.2.dist-info/METADATA
odoo_addon_l10n_it_abicab-18.0.1.0.0.2.dist-info/WHEEL
odoo_addon_l10n_it_abicab-18.0.1.0.0.2.dist-info/top_level.txt
odoo_addon_l10n_it_abicab-18.0.1.0.0.2.dist-info/RECORD
